{
    "height": 55,
    "target_rpm": [
        4000.0,
        4000.0,
        4000.0,
        4000.0
    ],
    "timestamp": 1711375918.8860478,
    "platform": "betaflight-2",
    "description": null,
    "compact": false,
    "frames": [
        {
            "t": 0.0,
            "accel": [
                [
                    -3.41,
                    2.279,
                    11.272
                ]
            ],
            "dist": [
                55.54634319790365
            ],
            "mass": [
                0.0,
                9.14,
                8.83
            ],
            "rpm": [
                3857,
                3757,
                3628,
                3771
            ],
            "audio": null,
            "dt": null,
            "fft_freq": null,
            "fft_ampl": null,
            "peak_freq": null,
            "peak_ampl": null,
            "compact": false
        },
        {
            "t": 0.4506685733795166,
            "accel": [
                [
                    -3.14,
                    0.704,
                    10.295
                ]
            ],
            "dist": [
                55.53763914495648
            ],
            "mass": [
                0.0,
                9.31,
                8.76
            ],
            "rpm": [
                3842,
                3771,
                3657,
                3700
            ],
            "audio": null,
            "dt": null,
            "fft_freq": null,
            "fft_ampl": null,
            "peak_freq": null,
            "peak_ampl": null,
            "compact": false
        },
        {
            "t": 0.9534153938293457,
            "accel": [
                [
                    -3.03,
                    0.172,
                    8.835
                ]
            ],
            "dist": [
                55.55949850324858
            ],
            "mass": [
                0.0,
                9.26,
                8.63
            ],
            "rpm": [
                3714,
                3642,
                3642,
                3700
            ],
            "audio": null,
            "dt": null,
            "fft_freq": null,
            "fft_ampl": null,
            "peak_freq": null,
            "peak_ampl": null,
            "compact": false
        },
        {
            "t": 1.4315965175628662,
            "accel": [
                [
                    -2.19,
                    0.105,
                    8.322
                ]
            ],
            "dist": [
                55.54634319790365
            ],
            "mass": [
                0.0,
                9.12,
                8.82
            ],
            "rpm": [
                3828,
                3714,
                3600,
                3800
            ],
            "audio": null,
            "dt": null,
            "fft_freq": null,
            "fft_ampl": null,
            "peak_freq": null,
            "peak_ampl": null,
            "compact": false
        },
        {
            "t": 1.8685541152954102,
            "accel": [
                [
                    -1.58,
                    1.35,
                    10.965
                ]
            ],
            "dist": [
                55.54634319790365
            ],
            "mass": [
                0.0,
                9.15,
                8.66
            ],
            "rpm": [
                3857,
                3700,
                3614,
                3771
            ],
            "audio": null,
            "dt": null,
            "fft_freq": null,
            "fft_ampl": null,
            "peak_freq": null,
            "peak_ampl": null,
            "compact": false
        },
        {
            "t": 2.3960013389587402,
            "accel": [
                [
                    -2.29,
                    -1.494,
                    9.074
                ]
            ],
            "dist": [
                55.54634319790365
            ],
            "mass": [
                0.0,
                9.09,
                8.73
            ],
            "rpm": [
                3814,
                3685,
                3642,
                3757
            ],
            "audio": null,
            "dt": null,
            "fft_freq": null,
            "fft_ampl": null,
            "peak_freq": null,
            "peak_ampl": null,
            "compact": false
        },
        {
            "t": 2.8697354793548584,
            "accel": [
                [
                    1.83,
                    2.868,
                    10.338
                ]
            ],
            "dist": [
                55.54634319790365
            ],
            "mass": [
                0.0,
                9.06,
                8.75
            ],
            "rpm": [
                3814,
                3757,
                3628,
                3700
            ],
            "audio": null,
            "dt": null,
            "fft_freq": null,
            "fft_ampl": null,
            "peak_freq": null,
            "peak_ampl": null,
            "compact": false
        },
        {
            "t": 3.3606984615325928,
            "accel": [
                [
                    1.53,
                    -0.383,
                    10.218
                ]
            ],
            "dist": [
                55.55949850324858
            ],
            "mass": [
                0.0,
                9.25,
                8.61
            ],
            "rpm": [
                3828,
                3714,
                3628,
                3757
            ],
            "audio": null,
            "dt": null,
            "fft_freq": null,
            "fft_ampl": null,
            "peak_freq": null,
            "peak_ampl": null,
            "compact": false
        },
        {
            "t": 3.794476270675659,
            "accel": [
                [
                    -1.56,
                    -1.767,
                    8.969
                ]
            ],
            "dist": [
                55.54634319790365
            ],
            "mass": [
                0.0,
                9.02,
                8.7
            ],
            "rpm": [
                3857,
                3685,
                3614,
                3714
            ],
            "audio": null,
            "dt": null,
            "fft_freq": null,
            "fft_ampl": null,
            "peak_freq": null,
            "peak_ampl": null,
            "compact": false
        },
        {
            "t": 4.224998474121094,
            "accel": [
                [
                    4.47,
                    1.796,
                    9.558
                ]
            ],
            "dist": [
                55.54611123739244
            ],
            "mass": [
                0.0,
                8.9,
                8.81
            ],
            "rpm": [
                3771,
                3657,
                3600,
                3714
            ],
            "audio": null,
            "dt": null,
            "fft_freq": null,
            "fft_ampl": null,
            "peak_freq": null,
            "peak_ampl": null,
            "compact": false
        },
        {
            "t": 4.715409517288208,
            "accel": [
                [
                    -0.88,
                    0.096,
                    11.827
                ]
            ],
            "dist": [
                55.54634319790365
            ],
            "mass": [
                0.0,
                9.01,
                8.7
            ],
            "rpm": [
                3828,
                3742,
                3614,
                3757
            ],
            "audio": null,
            "dt": null,
            "fft_freq": null,
            "fft_ampl": null,
            "peak_freq": null,
            "peak_ampl": null,
            "compact": false
        },
        {
            "t": 5.149551868438721,
            "accel": [
                [
                    -0.23,
                    0.192,
                    13.259
                ]
            ],
            "dist": [
                55.54634319790365
            ],
            "mass": [
                0.0,
                9.04,
                8.58
            ],
            "rpm": [
                3842,
                3657,
                3614,
                3728
            ],
            "audio": null,
            "dt": null,
            "fft_freq": null,
            "fft_ampl": null,
            "peak_freq": null,
            "peak_ampl": null,
            "compact": false
        },
        {
            "t": 5.593986988067627,
            "accel": [
                [
                    -1.95,
                    1.858,
                    11.186
                ]
            ],
            "dist": [
                55.53990896012246
            ],
            "mass": [
                0.0,
                8.9,
                8.89
            ],
            "rpm": [
                3728,
                3714,
                3671,
                3728
            ],
            "audio": null,
            "dt": null,
            "fft_freq": null,
            "fft_ampl": null,
            "peak_freq": null,
            "peak_ampl": null,
            "compact": false
        },
        {
            "t": 6.001480340957642,
            "accel": [
                [
                    -1.6,
                    2.562,
                    7.647
                ]
            ],
            "dist": [
                55.54634319790365
            ],
            "mass": [
                0.0,
                9.0,
                8.78
            ],
            "rpm": [
                3828,
                3728,
                3642,
                3785
            ],
            "audio": null,
            "dt": null,
            "fft_freq": null,
            "fft_ampl": null,
            "peak_freq": null,
            "peak_ampl": null,
            "compact": false
        },
        {
            "t": 6.46874213218689,
            "accel": [
                [
                    -0.33,
                    1.164,
                    8.648
                ]
            ],
            "dist": [
                55.553175050763116
            ],
            "mass": [
                0.0,
                8.97,
                8.76
            ],
            "rpm": [
                3757,
                3714,
                3700,
                3700
            ],
            "audio": null,
            "dt": null,
            "fft_freq": null,
            "fft_ampl": null,
            "peak_freq": null,
            "peak_ampl": null,
            "compact": false
        },
        {
            "t": 6.96506142616272,
            "accel": [
                [
                    -2.38,
                    2.562,
                    9.759
                ]
            ],
            "dist": [
                55.54634319790365
            ],
            "mass": [
                0.0,
                8.95,
                8.87
            ],
            "rpm": [
                3814,
                3771,
                3642,
                3642
            ],
            "audio": null,
            "dt": null,
            "fft_freq": null,
            "fft_ampl": null,
            "peak_freq": null,
            "peak_ampl": null,
            "compact": false
        },
        {
            "t": 7.441429853439331,
            "accel": [
                [
                    -2.24,
                    -0.393,
                    12.431
                ]
            ],
            "dist": [
                55.55949850324858
            ],
            "mass": [
                0.0,
                8.94,
                8.74
            ],
            "rpm": [
                3771,
                3728,
                3671,
                3714
            ],
            "audio": null,
            "dt": null,
            "fft_freq": null,
            "fft_ampl": null,
            "peak_freq": null,
            "peak_ampl": null,
            "compact": false
        },
        {
            "t": 7.882290601730347,
            "accel": [
                [
                    1.2,
                    -0.622,
                    11.478
                ]
            ],
            "dist": [
                55.54634319790365
            ],
            "mass": [
                0.0,
                8.85,
                8.87
            ],
            "rpm": [
                3857,
                3714,
                3685,
                3657
            ],
            "audio": null,
            "dt": null,
            "fft_freq": null,
            "fft_ampl": null,
            "peak_freq": null,
            "peak_ampl": null,
            "compact": false
        },
        {
            "t": 8.390263319015503,
            "accel": [
                [
                    2.01,
                    -0.273,
                    9.036
                ]
            ],
            "dist": [
                55.54634319790365
            ],
            "mass": [
                0.0,
                8.96,
                8.9
            ],
            "rpm": [
                3771,
                3671,
                3614,
                3700
            ],
            "audio": null,
            "dt": null,
            "fft_freq": null,
            "fft_ampl": null,
            "peak_freq": null,
            "peak_ampl": null,
            "compact": false
        },
        {
            "t": 8.822866201400757,
            "accel": [
                [
                    -1.91,
                    1.14,
                    10.702
                ]
            ],
            "dist": [
                55.54663921957514
            ],
            "mass": [
                0.0,
                8.81,
                8.88
            ],
            "rpm": [
                3814,
                3714,
                3614,
                3742
            ],
            "audio": null,
            "dt": null,
            "fft_freq": null,
            "fft_ampl": null,
            "peak_freq": null,
            "peak_ampl": null,
            "compact": false
        },
        {
            "t": 9.336451053619385,
            "accel": [
                [
                    -4.64,
                    -0.172,
                    9.845
                ]
            ],
            "dist": [
                55.53299214449417
            ],
            "mass": [
                0.0,
                8.99,
                9.03
            ],
            "rpm": [
                3828,
                3700,
                3657,
                3785
            ],
            "audio": null,
            "dt": null,
            "fft_freq": null,
            "fft_ampl": null,
            "peak_freq": null,
            "peak_ampl": null,
            "compact": false
        },
        {
            "t": 9.815282344818115,
            "accel": [
                [
                    2.33,
                    -0.22,
                    10.118
                ]
            ],
            "dist": [
                55.54634319790365
            ],
            "mass": [
                0.0,
                8.74,
                8.96
            ],
            "rpm": [
                3842,
                3728,
                3642,
                3714
            ],
            "audio": null,
            "dt": null,
            "fft_freq": null,
            "fft_ampl": null,
            "peak_freq": null,
            "peak_ampl": null,
            "compact": false
        },
        {
            "t": 10.262032270431519,
            "accel": [
                [
                    -0.39,
                    -2.452,
                    10.104
                ]
            ],
            "dist": [
                55.54611123739244
            ],
            "mass": [
                0.0,
                9.05,
                8.91
            ],
            "rpm": [
                3785,
                3728,
                3585,
                3771
            ],
            "audio": null,
            "dt": null,
            "fft_freq": null,
            "fft_ampl": null,
            "peak_freq": null,
            "peak_ampl": null,
            "compact": false
        },
        {
            "t": 10.77868914604187,
            "accel": [
                [
                    -4.28,
                    -0.311,
                    8.294
                ]
            ],
            "dist": [
                55.54211070630086
            ],
            "mass": [
                0.0,
                9.08,
                8.94
            ],
            "rpm": [
                3742,
                3685,
                3671,
                3728
            ],
            "audio": null,
            "dt": null,
            "fft_freq": null,
            "fft_ampl": null,
            "peak_freq": null,
            "peak_ampl": null,
            "compact": false
        },
        {
            "t": 11.264564275741577,
            "accel": [
                [
                    1.68,
                    -0.402,
                    11.736
                ]
            ],
            "dist": [
                55.54634319790365
            ],
            "mass": [
                0.0,
                8.63,
                8.99
            ],
            "rpm": [
                3800,
                3714,
                3614,
                3728
            ],
            "audio": null,
            "dt": null,
            "fft_freq": null,
            "fft_ampl": null,
            "peak_freq": null,
            "peak_ampl": null,
            "compact": false
        },
        {
            "t": 11.744203567504883,
            "accel": [
                [
                    0.24,
                    -0.575,
                    10.391
                ]
            ],
            "dist": [
                55.54634319790365
            ],
            "mass": [
                0.0,
                8.98,
                8.96
            ],
            "rpm": [
                3828,
                3642,
                3642,
                3700
            ],
            "audio": null,
            "dt": null,
            "fft_freq": null,
            "fft_ampl": null,
            "peak_freq": null,
            "peak_ampl": null,
            "compact": false
        },
        {
            "t": 12.215277671813965,
            "accel": [
                [
                    -4.25,
                    1.772,
                    9.936
                ]
            ],
            "dist": [
                55.53299214449417
            ],
            "mass": [
                0.0,
                9.15,
                8.92
            ],
            "rpm": [
                3828,
                3700,
                3614,
                3714
            ],
            "audio": null,
            "dt": null,
            "fft_freq": null,
            "fft_ampl": null,
            "peak_freq": null,
            "peak_ampl": null,
            "compact": false
        },
        {
            "t": 12.636598587036133,
            "accel": [
                [
                    -0.78,
                    0.124,
                    8.375
                ]
            ],
            "dist": [
                55.53990896012246
            ],
            "mass": [
                0.0,
                9.15,
                8.83
            ],
            "rpm": [
                3828,
                3714,
                3657,
                3700
            ],
            "audio": null,
            "dt": null,
            "fft_freq": null,
            "fft_ampl": null,
            "peak_freq": null,
            "peak_ampl": null,
            "compact": false
        },
        {
            "t": 13.132218599319458,
            "accel": [
                [
                    1.7,
                    0.302,
                    7.743
                ]
            ],
            "dist": [
                55.53299214449417
            ],
            "mass": [
                0.0,
                9.23,
                8.73
            ],
            "rpm": [
                3842,
                3714,
                3642,
                3800
            ],
            "audio": null,
            "dt": null,
            "fft_freq": null,
            "fft_ampl": null,
            "peak_freq": null,
            "peak_ampl": null,
            "compact": false
        },
        {
            "t": 13.680899143218994,
            "accel": [
                [
                    1.15,
                    -0.373,
                    7.748
                ]
            ],
            "dist": [
                55.54611123739244
            ],
            "mass": [
                0.0,
                9.22,
                8.58
            ],
            "rpm": [
                3885,
                3728,
                3642,
                3714
            ],
            "audio": null,
            "dt": null,
            "fft_freq": null,
            "fft_ampl": null,
            "peak_freq": null,
            "peak_ampl": null,
            "compact": false
        },
        {
            "t": 14.121776580810547,
            "accel": [
                [
                    -3.2,
                    -0.57,
                    9.807
                ]
            ],
            "dist": [
                55.53299214449417
            ],
            "mass": [
                0.0,
                9.19,
                8.66
            ],
            "rpm": [
                3857,
                3700,
                3614,
                3728
            ],
            "audio": null,
            "dt": null,
            "fft_freq": null,
            "fft_ampl": null,
            "peak_freq": null,
            "peak_ampl": null,
            "compact": false
        },
        {
            "t": 14.591662406921387,
            "accel": [
                [
                    1.18,
                    -1.508,
                    7.815
                ]
            ],
            "dist": [
                55.5459402586393
            ],
            "mass": [
                0.0,
                9.14,
                8.81
            ],
            "rpm": [
                3828,
                3642,
                3685,
                3814
            ],
            "audio": null,
            "dt": null,
            "fft_freq": null,
            "fft_ampl": null,
            "peak_freq": null,
            "peak_ampl": null,
            "compact": false
        },
        {
            "t": 15.107623815536499,
            "accel": [
                [
                    -0.11,
                    0.244,
                    11.2
                ]
            ],
            "dist": [
                55.54634319790365
            ],
            "mass": [
                0.0,
                9.08,
                8.93
            ],
            "rpm": [
                3842,
                3714,
                3614,
                3700
            ],
            "audio": null,
            "dt": null,
            "fft_freq": null,
            "fft_ampl": null,
            "peak_freq": null,
            "peak_ampl": null,
            "compact": false
        },
        {
            "t": 15.577993631362915,
            "accel": [
                [
                    1.16,
                    0.68,
                    10.448
                ]
            ],
            "dist": [
                55.54634319790365
            ],
            "mass": [
                0.0,
                9.25,
                8.83
            ],
            "rpm": [
                3771,
                3714,
                3628,
                3785
            ],
            "audio": null,
            "dt": null,
            "fft_freq": null,
            "fft_ampl": null,
            "peak_freq": null,
            "peak_ampl": null,
            "compact": false
        },
        {
            "t": 16.07534956932068,
            "accel": [
                [
                    3.62,
                    -1.408,
                    12.507
                ]
            ],
            "dist": [
                55.54634319790365
            ],
            "mass": [
                0.0,
                9.41,
                8.74
            ],
            "rpm": [
                3900,
                3714,
                3671,
                3714
            ],
            "audio": null,
            "dt": null,
            "fft_freq": null,
            "fft_ampl": null,
            "peak_freq": null,
            "peak_ampl": null,
            "compact": false
        },
        {
            "t": 16.489412546157837,
            "accel": [
                [
                    1.87,
                    -1.628,
                    13.144
                ]
            ],
            "dist": [
                55.55949850324858
            ],
            "mass": [
                0.0,
                9.24,
                8.73
            ],
            "rpm": [
                3885,
                3728,
                3614,
                3742
            ],
            "audio": null,
            "dt": null,
            "fft_freq": null,
            "fft_ampl": null,
            "peak_freq": null,
            "peak_ampl": null,
            "compact": false
        },
        {
            "t": 16.934069871902466,
            "accel": [
                [
                    -3.94,
                    -1.235,
                    8.772
                ]
            ],
            "dist": [
                55.54634319790365
            ],
            "mass": [
                0.0,
                9.1,
                8.81
            ],
            "rpm": [
                3757,
                3714,
                3600,
                3714
            ],
            "audio": null,
            "dt": null,
            "fft_freq": null,
            "fft_ampl": null,
            "peak_freq": null,
            "peak_ampl": null,
            "compact": false
        },
        {
            "t": 17.416409015655518,
            "accel": [
                [
                    3.83,
                    1.772,
                    11.971
                ]
            ],
            "dist": [
                55.55926699529645
            ],
            "mass": [
                0.0,
                9.01,
                8.94
            ],
            "rpm": [
                3828,
                3671,
                3642,
                3728
            ],
            "audio": null,
            "dt": null,
            "fft_freq": null,
            "fft_ampl": null,
            "peak_freq": null,
            "peak_ampl": null,
            "compact": false
        },
        {
            "t": 17.871219635009766,
            "accel": [
                [
                    -4.03,
                    -0.096,
                    11.459
                ]
            ],
            "dist": [
                55.53334251509387
            ],
            "mass": [
                0.0,
                9.11,
                8.82
            ],
            "rpm": [
                3785,
                3728,
                3671,
                3728
            ],
            "audio": null,
            "dt": null,
            "fft_freq": null,
            "fft_ampl": null,
            "peak_freq": null,
            "peak_ampl": null,
            "compact": false
        },
        {
            "t": 18.363739013671875,
            "accel": [
                [
                    0.58,
                    -0.608,
                    10.568
                ]
            ],
            "dist": [
                55.54634319790365
            ],
            "mass": [
                0.0,
                9.02,
                8.77
            ],
            "rpm": [
                3757,
                3700,
                3614,
                3771
            ],
            "audio": null,
            "dt": null,
            "fft_freq": null,
            "fft_ampl": null,
            "peak_freq": null,
            "peak_ampl": null,
            "compact": false
        },
        {
            "t": 18.831135272979736,
            "accel": [
                [
                    -0.94,
                    0.579,
                    8.796
                ]
            ],
            "dist": [
                55.53990896012246
            ],
            "mass": [
                0.0,
                9.31,
                8.69
            ],
            "rpm": [
                3757,
                3728,
                3600,
                3742
            ],
            "audio": null,
            "dt": null,
            "fft_freq": null,
            "fft_ampl": null,
            "peak_freq": null,
            "peak_ampl": null,
            "compact": false
        },
        {
            "t": 19.307291746139526,
            "accel": [
                [
                    0.82,
                    1.245,
                    11.248
                ]
            ],
            "dist": [
                55.54634319790365
            ],
            "mass": [
                0.0,
                9.24,
                8.79
            ],
            "rpm": [
                3857,
                3685,
                3614,
                3771
            ],
            "audio": null,
            "dt": null,
            "fft_freq": null,
            "fft_ampl": null,
            "peak_freq": null,
            "peak_ampl": null,
            "compact": false
        },
        {
            "t": 19.820956230163574,
            "accel": [
                [
                    2.55,
                    -0.694,
                    8.777
                ]
            ],
            "dist": [
                55.55949850324858
            ],
            "mass": [
                0.0,
                9.05,
                8.66
            ],
            "rpm": [
                3757,
                3742,
                3614,
                3714
            ],
            "audio": null,
            "dt": null,
            "fft_freq": null,
            "fft_ampl": null,
            "peak_freq": null,
            "peak_ampl": null,
            "compact": false
        },
        {
            "t": 20.30790066719055,
            "accel": [
                [
                    -0.15,
                    1.144,
                    12.412
                ]
            ],
            "dist": [
                55.54663921957514
            ],
            "mass": [
                0.0,
                9.05,
                8.85
            ],
            "rpm": [
                3828,
                3700,
                3685,
                3728
            ],
            "audio": null,
            "dt": null,
            "fft_freq": null,
            "fft_ampl": null,
            "peak_freq": null,
            "peak_ampl": null,
            "compact": false
        },
        {
            "t": 20.818581342697144,
            "accel": [
                [
                    1.03,
                    -0.881,
                    11.602
                ]
            ],
            "dist": [
                55.53299214449417
            ],
            "mass": [
                0.0,
                9.21,
                8.64
            ],
            "rpm": [
                3800,
                3685,
                3614,
                3714
            ],
            "audio": null,
            "dt": null,
            "fft_freq": null,
            "fft_ampl": null,
            "peak_freq": null,
            "peak_ampl": null,
            "compact": false
        },
        {
            "t": 21.276002883911133,
            "accel": [
                [
                    -2.43,
                    -0.388,
                    10.415
                ]
            ],
            "dist": [
                55.54634319790365
            ],
            "mass": [
                0.0,
                9.08,
                8.58
            ],
            "rpm": [
                3757,
                3714,
                3600,
                3657
            ],
            "audio": null,
            "dt": null,
            "fft_freq": null,
            "fft_ampl": null,
            "peak_freq": null,
            "peak_ampl": null,
            "compact": false
        },
        {
            "t": 21.77391242980957,
            "accel": [
                [
                    0.74,
                    -2.097,
                    11.349
                ]
            ],
            "dist": [
                55.54611123739244
            ],
            "mass": [
                0.0,
                9.2,
                8.64
            ],
            "rpm": [
                3785,
                3700,
                3685,
                3757
            ],
            "audio": null,
            "dt": null,
            "fft_freq": null,
            "fft_ampl": null,
            "peak_freq": null,
            "peak_ampl": null,
            "compact": false
        },
        {
            "t": 22.236966133117676,
            "accel": [
                [
                    -2.62,
                    0.196,
                    8.586
                ]
            ],
            "dist": [
                55.54663921957514
            ],
            "mass": [
                0.0,
                9.14,
                8.74
            ],
            "rpm": [
                3785,
                3671,
                3614,
                3728
            ],
            "audio": null,
            "dt": null,
            "fft_freq": null,
            "fft_ampl": null,
            "peak_freq": null,
            "peak_ampl": null,
            "compact": false
        },
        {
            "t": 22.738529682159424,
            "accel": [
                [
                    0.28,
                    0.622,
                    11.181
                ]
            ],
            "dist": [
                55.54634319790365
            ],
            "mass": [
                0.0,
                9.18,
                8.69
            ],
            "rpm": [
                3857,
                3714,
                3614,
                3742
            ],
            "audio": null,
            "dt": null,
            "fft_freq": null,
            "fft_ampl": null,
            "peak_freq": null,
            "peak_ampl": null,
            "compact": false
        },
        {
            "t": 23.233288049697876,
            "accel": [
                [
                    0.45,
                    -0.278,
                    10.29
                ]
            ],
            "dist": [
                55.53299214449417
            ],
            "mass": [
                0.0,
                9.35,
                8.87
            ],
            "rpm": [
                3800,
                3642,
                3614,
                3800
            ],
            "audio": null,
            "dt": null,
            "fft_freq": null,
            "fft_ampl": null,
            "peak_freq": null,
            "peak_ampl": null,
            "compact": false
        },
        {
            "t": 23.661447048187256,
            "accel": [
                [
                    0.3,
                    0.364,
                    9.342
                ]
            ],
            "dist": [
                55.54634319790365
            ],
            "mass": [
                0.0,
                9.49,
                8.7
            ],
            "rpm": [
                3828,
                3714,
                3600,
                3714
            ],
            "audio": null,
            "dt": null,
            "fft_freq": null,
            "fft_ampl": null,
            "peak_freq": null,
            "peak_ampl": null,
            "compact": false
        },
        {
            "t": 24.145551204681396,
            "accel": [
                [
                    -0.21,
                    1.082,
                    8.294
                ]
            ],
            "dist": [
                55.54634319790365
            ],
            "mass": [
                0.0,
                9.6,
                8.68
            ],
            "rpm": [
                3842,
                3728,
                3600,
                3700
            ],
            "audio": null,
            "dt": null,
            "fft_freq": null,
            "fft_ampl": null,
            "peak_freq": null,
            "peak_ampl": null,
            "compact": false
        },
        {
            "t": 24.61963152885437,
            "accel": [
                [
                    1.53,
                    -1.978,
                    8.768
                ]
            ],
            "dist": [
                55.55949850324858
            ],
            "mass": [
                0.0,
                9.38,
                8.76
            ],
            "rpm": [
                3814,
                3685,
                3614,
                3728
            ],
            "audio": null,
            "dt": null,
            "fft_freq": null,
            "fft_ampl": null,
            "peak_freq": null,
            "peak_ampl": null,
            "compact": false
        },
        {
            "t": 25.150987148284912,
            "accel": [
                [
                    2.21,
                    -0.244,
                    9.553
                ]
            ],
            "dist": [
                55.55926699529645
            ],
            "mass": [
                0.0,
                9.41,
                8.75
            ],
            "rpm": [
                3728,
                3685,
                3628,
                3742
            ],
            "audio": null,
            "dt": null,
            "fft_freq": null,
            "fft_ampl": null,
            "peak_freq": null,
            "peak_ampl": null,
            "compact": false
        },
        {
            "t": 25.63271689414978,
            "accel": [
                [
                    0.65,
                    -0.776,
                    9.74
                ]
            ],
            "dist": [
                55.53334251509387
            ],
            "mass": [
                0.0,
                9.26,
                8.83
            ],
            "rpm": [
                3771,
                3771,
                3685,
                3742
            ],
            "audio": null,
            "dt": null,
            "fft_freq": null,
            "fft_ampl": null,
            "peak_freq": null,
            "peak_ampl": null,
            "compact": false
        },
        {
            "t": 26.0690279006958,
            "accel": [
                [
                    0.41,
                    -0.948,
                    10.458
                ]
            ],
            "dist": [
                55.54634319790365
            ],
            "mass": [
                0.0,
                8.92,
                8.94
            ],
            "rpm": [
                3828,
                3771,
                3628,
                3742
            ],
            "audio": null,
            "dt": null,
            "fft_freq": null,
            "fft_ampl": null,
            "peak_freq": null,
            "peak_ampl": null,
            "compact": false
        },
        {
            "t": 26.550751209259033,
            "accel": [
                [
                    0.55,
                    -0.532,
                    7.379
                ]
            ],
            "dist": [
                55.54634319790365
            ],
            "mass": [
                0.0,
                9.22,
                8.72
            ],
            "rpm": [
                3814,
                3714,
                3671,
                3728
            ],
            "audio": null,
            "dt": null,
            "fft_freq": null,
            "fft_ampl": null,
            "peak_freq": null,
            "peak_ampl": null,
            "compact": false
        },
        {
            "t": 26.99389886856079,
            "accel": [
                [
                    -0.45,
                    -0.12,
                    12.287
                ]
            ],
            "dist": [
                55.53299214449417
            ],
            "mass": [
                0.0,
                8.96,
                8.98
            ],
            "rpm": [
                3800,
                3728,
                3671,
                3714
            ],
            "audio": null,
            "dt": null,
            "fft_freq": null,
            "fft_ampl": null,
            "peak_freq": null,
            "peak_ampl": null,
            "compact": false
        },
        {
            "t": 27.475539207458496,
            "accel": [
                [
                    1.05,
                    -1.135,
                    12.814
                ]
            ],
            "dist": [
                55.54611123739244
            ],
            "mass": [
                0.0,
                9.42,
                8.81
            ],
            "rpm": [
                3828,
                3657,
                3642,
                3685
            ],
            "audio": null,
            "dt": null,
            "fft_freq": null,
            "fft_ampl": null,
            "peak_freq": null,
            "peak_ampl": null,
            "compact": false
        },
        {
            "t": 27.91828465461731,
            "accel": [
                [
                    2.04,
                    -1.867,
                    10.874
                ]
            ],
            "dist": [
                55.53334251509387
            ],
            "mass": [
                0.0,
                9.3,
                8.86
            ],
            "rpm": [
                3828,
                3685,
                3628,
                3714
            ],
            "audio": null,
            "dt": null,
            "fft_freq": null,
            "fft_ampl": null,
            "peak_freq": null,
            "peak_ampl": null,
            "compact": false
        },
        {
            "t": 28.354390621185303,
            "accel": [
                [
                    -3.19,
                    0.666,
                    8.921
                ]
            ],
            "dist": [
                55.55949850324858
            ],
            "mass": [
                0.0,
                9.38,
                8.96
            ],
            "rpm": [
                3842,
                3714,
                3585,
                3742
            ],
            "audio": null,
            "dt": null,
            "fft_freq": null,
            "fft_ampl": null,
            "peak_freq": null,
            "peak_ampl": null,
            "compact": false
        },
        {
            "t": 28.798869132995605,
            "accel": [
                [
                    -0.01,
                    -1.748,
                    11.559
                ]
            ],
            "dist": [
                55.55949850324858
            ],
            "mass": [
                0.0,
                9.15,
                8.75
            ],
            "rpm": [
                3785,
                3642,
                3642,
                3714
            ],
            "audio": null,
            "dt": null,
            "fft_freq": null,
            "fft_ampl": null,
            "peak_freq": null,
            "peak_ampl": null,
            "compact": false
        },
        {
            "t": 29.244964122772217,
            "accel": [
                [
                    -0.85,
                    0.891,
                    8.93
                ]
            ],
            "dist": [
                55.53299214449417
            ],
            "mass": [
                0.0,
                9.0,
                8.84
            ],
            "rpm": [
                3900,
                3771,
                3600,
                3685
            ],
            "audio": null,
            "dt": null,
            "fft_freq": null,
            "fft_ampl": null,
            "peak_freq": null,
            "peak_ampl": null,
            "compact": false
        },
        {
            "t": 29.801482439041138,
            "accel": [
                [
                    4.11,
                    -1.566,
                    9.088
                ]
            ],
            "dist": [
                55.53299214449417
            ],
            "mass": [
                0.0,
                9.26,
                8.73
            ],
            "rpm": [
                3800,
                3728,
                3714,
                3800
            ],
            "audio": null,
            "dt": null,
            "fft_freq": null,
            "fft_ampl": null,
            "peak_freq": null,
            "peak_ampl": null,
            "compact": false
        }
    ]
}