{
    "height": 75,
    "target_rpm": [
        6000.0,
        6000.0,
        6000.0,
        6000.0
    ],
    "timestamp": 1711375918.8860478,
    "platform": "betaflight-2",
    "description": null,
    "compact": false,
    "frames": [
        {
            "t": 0.0,
            "accel": [
                [
                    0.51,
                    0.867,
                    10.611
                ]
            ],
            "dist": [
                76.89408212635469
            ],
            "mass": [
                0.0,
                22.64,
                22.03
            ],
            "rpm": [
                5471,
                5457,
                5542,
                5442
            ],
            "audio": null,
            "dt": null,
            "fft_freq": null,
            "fft_ampl": null,
            "peak_freq": null,
            "peak_ampl": null,
            "compact": false
        },
        {
            "t": 0.4894287586212158,
            "accel": [
                [
                    -0.81,
                    -1.724,
                    9.754
                ]
            ],
            "dist": [
                76.87511824278754
            ],
            "mass": [
                0.0,
                22.54,
                22.48
            ],
            "rpm": [
                5557,
                5657,
                5428,
                5542
            ],
            "audio": null,
            "dt": null,
            "fft_freq": null,
            "fft_ampl": null,
            "peak_freq": null,
            "peak_ampl": null,
            "compact": false
        },
        {
            "t": 0.9962389469146729,
            "accel": [
                [
                    -1.33,
                    -0.828,
                    10.472
                ]
            ],
            "dist": [
                76.88898163129767
            ],
            "mass": [
                0.0,
                22.72,
                22.28
            ],
            "rpm": [
                5614,
                5442,
                5628,
                5385
            ],
            "audio": null,
            "dt": null,
            "fft_freq": null,
            "fft_ampl": null,
            "peak_freq": null,
            "peak_ampl": null,
            "compact": false
        },
        {
            "t": 1.5064375400543213,
            "accel": [
                [
                    0.28,
                    0.948,
                    10.592
                ]
            ],
            "dist": [
                76.8791741616126
            ],
            "mass": [
                0.0,
                22.7,
                22.25
            ],
            "rpm": [
                5528,
                5471,
                5514,
                5542
            ],
            "audio": null,
            "dt": null,
            "fft_freq": null,
            "fft_ampl": null,
            "peak_freq": null,
            "peak_ampl": null,
            "compact": false
        },
        {
            "t": 2.012228488922119,
            "accel": [
                [
                    -0.72,
                    -1.911,
                    10.324
                ]
            ],
            "dist": [
                76.90245553643143
            ],
            "mass": [
                0.0,
                22.46,
                22.33
            ],
            "rpm": [
                5600,
                5500,
                5628,
                5500
            ],
            "audio": null,
            "dt": null,
            "fft_freq": null,
            "fft_ampl": null,
            "peak_freq": null,
            "peak_ampl": null,
            "compact": false
        },
        {
            "t": 2.5069143772125244,
            "accel": [
                [
                    0.82,
                    -1.35,
                    10.506
                ]
            ],
            "dist": [
                76.88893016325322
            ],
            "mass": [
                0.0,
                22.41,
                22.24
            ],
            "rpm": [
                5528,
                5414,
                5571,
                5400
            ],
            "audio": null,
            "dt": null,
            "fft_freq": null,
            "fft_ampl": null,
            "peak_freq": null,
            "peak_ampl": null,
            "compact": false
        },
        {
            "t": 2.9429471492767334,
            "accel": [
                [
                    -0.02,
                    0.101,
                    9.778
                ]
            ],
            "dist": [
                76.88899443716346
            ],
            "mass": [
                0.0,
                22.26,
                22.21
            ],
            "rpm": [
                5614,
                5428,
                5571,
                5571
            ],
            "audio": null,
            "dt": null,
            "fft_freq": null,
            "fft_ampl": null,
            "peak_freq": null,
            "peak_ampl": null,
            "compact": false
        },
        {
            "t": 3.473606824874878,
            "accel": [
                [
                    -0.45,
                    1.762,
                    8.94
                ]
            ],
            "dist": [
                76.88893016325322
            ],
            "mass": [
                0.0,
                22.49,
                22.4
            ],
            "rpm": [
                5757,
                5657,
                5385,
                5628
            ],
            "audio": null,
            "dt": null,
            "fft_freq": null,
            "fft_ampl": null,
            "peak_freq": null,
            "peak_ampl": null,
            "compact": false
        },
        {
            "t": 3.9471919536590576,
            "accel": [
                [
                    -0.51,
                    -0.053,
                    9.151
                ]
            ],
            "dist": [
                76.88369045604054
            ],
            "mass": [
                0.0,
                22.67,
                22.32
            ],
            "rpm": [
                5571,
                5414,
                5557,
                5428
            ],
            "audio": null,
            "dt": null,
            "fft_freq": null,
            "fft_ampl": null,
            "peak_freq": null,
            "peak_ampl": null,
            "compact": false
        },
        {
            "t": 4.424850225448608,
            "accel": [
                [
                    -0.67,
                    0.287,
                    8.916
                ]
            ],
            "dist": [
                76.87511824278754
            ],
            "mass": [
                0.0,
                22.5,
                22.46
            ],
            "rpm": [
                5557,
                5614,
                5657,
                5657
            ],
            "audio": null,
            "dt": null,
            "fft_freq": null,
            "fft_ampl": null,
            "peak_freq": null,
            "peak_ampl": null,
            "compact": false
        },
        {
            "t": 4.909763336181641,
            "accel": [
                [
                    -0.19,
                    -0.871,
                    10.587
                ]
            ],
            "dist": [
                76.89428812730176
            ],
            "mass": [
                0.0,
                22.73,
                22.44
            ],
            "rpm": [
                5585,
                5657,
                5442,
                5328
            ],
            "audio": null,
            "dt": null,
            "fft_freq": null,
            "fft_ampl": null,
            "peak_freq": null,
            "peak_ampl": null,
            "compact": false
        },
        {
            "t": 5.346583366394043,
            "accel": [
                [
                    2.04,
                    -0.378,
                    8.715
                ]
            ],
            "dist": [
                76.88893016325322
            ],
            "mass": [
                0.0,
                22.83,
                22.51
            ],
            "rpm": [
                5357,
                5585,
                5628,
                5671
            ],
            "audio": null,
            "dt": null,
            "fft_freq": null,
            "fft_ampl": null,
            "peak_freq": null,
            "peak_ampl": null,
            "compact": false
        },
        {
            "t": 5.794325590133667,
            "accel": [
                [
                    -1.62,
                    -0.608,
                    10.214
                ]
            ],
            "dist": [
                76.88872473667725
            ],
            "mass": [
                0.0,
                22.76,
                22.52
            ],
            "rpm": [
                5600,
                5700,
                5571,
                5428
            ],
            "audio": null,
            "dt": null,
            "fft_freq": null,
            "fft_ampl": null,
            "peak_freq": null,
            "peak_ampl": null,
            "compact": false
        },
        {
            "t": 6.308861255645752,
            "accel": [
                [
                    0.89,
                    -1.202,
                    9.093
                ]
            ],
            "dist": [
                76.88893016325322
            ],
            "mass": [
                0.0,
                23.03,
                22.26
            ],
            "rpm": [
                5514,
                5600,
                5528,
                5414
            ],
            "audio": null,
            "dt": null,
            "fft_freq": null,
            "fft_ampl": null,
            "peak_freq": null,
            "peak_ampl": null,
            "compact": false
        },
        {
            "t": 6.713834285736084,
            "accel": [
                [
                    0.85,
                    2.835,
                    9.84
                ]
            ],
            "dist": [
                76.80500641212554
            ],
            "mass": [
                0.0,
                22.44,
                21.95
            ],
            "rpm": [
                5471,
                5600,
                5528,
                5571
            ],
            "audio": null,
            "dt": null,
            "fft_freq": null,
            "fft_ampl": null,
            "peak_freq": null,
            "peak_ampl": null,
            "compact": false
        },
        {
            "t": 7.176917552947998,
            "accel": [
                [
                    -0.53,
                    0.168,
                    9.72
                ]
            ],
            "dist": [
                76.89454997654678
            ],
            "mass": [
                0.0,
                22.54,
                22.44
            ],
            "rpm": [
                5457,
                5614,
                5457,
                5500
            ],
            "audio": null,
            "dt": null,
            "fft_freq": null,
            "fft_ampl": null,
            "peak_freq": null,
            "peak_ampl": null,
            "compact": false
        },
        {
            "t": 7.653082609176636,
            "accel": [
                [
                    -0.45,
                    -2.308,
                    8.246
                ]
            ],
            "dist": [
                76.88887230562787
            ],
            "mass": [
                0.0,
                22.78,
                22.19
            ],
            "rpm": [
                5385,
                5485,
                5571,
                5614
            ],
            "audio": null,
            "dt": null,
            "fft_freq": null,
            "fft_ampl": null,
            "peak_freq": null,
            "peak_ampl": null,
            "compact": false
        },
        {
            "t": 8.088250398635864,
            "accel": [
                [
                    -0.29,
                    -2.255,
                    11.047
                ]
            ],
            "dist": [
                76.89808413436509
            ],
            "mass": [
                0.0,
                22.95,
                22.02
            ],
            "rpm": [
                5471,
                5642,
                5457,
                5614
            ],
            "audio": null,
            "dt": null,
            "fft_freq": null,
            "fft_ampl": null,
            "peak_freq": null,
            "peak_ampl": null,
            "compact": false
        },
        {
            "t": 8.497435569763184,
            "accel": [
                [
                    3.35,
                    1.259,
                    9.701
                ]
            ],
            "dist": [
                76.88887396064773
            ],
            "mass": [
                0.0,
                21.96,
                22.65
            ],
            "rpm": [
                5642,
                5414,
                5557,
                5614
            ],
            "audio": null,
            "dt": null,
            "fft_freq": null,
            "fft_ampl": null,
            "peak_freq": null,
            "peak_ampl": null,
            "compact": false
        },
        {
            "t": 8.988671779632568,
            "accel": [
                [
                    0.97,
                    0.498,
                    10.726
                ]
            ],
            "dist": [
                76.91231199251615
            ],
            "mass": [
                0.0,
                22.76,
                22.09
            ],
            "rpm": [
                5457,
                5642,
                5600,
                5471
            ],
            "audio": null,
            "dt": null,
            "fft_freq": null,
            "fft_ampl": null,
            "peak_freq": null,
            "peak_ampl": null,
            "compact": false
        },
        {
            "t": 9.428391695022583,
            "accel": [
                [
                    2.31,
                    -0.646,
                    10.29
                ]
            ],
            "dist": [
                76.78660237173598
            ],
            "mass": [
                0.0,
                22.88,
                22.04
            ],
            "rpm": [
                5471,
                5428,
                5628,
                5571
            ],
            "audio": null,
            "dt": null,
            "fft_freq": null,
            "fft_ampl": null,
            "peak_freq": null,
            "peak_ampl": null,
            "compact": false
        },
        {
            "t": 9.894941568374634,
            "accel": [
                [
                    -2.54,
                    0.297,
                    9.931
                ]
            ],
            "dist": [
                76.89370485123237
            ],
            "mass": [
                0.0,
                22.6,
                21.87
            ],
            "rpm": [
                5557,
                5585,
                5628,
                5571
            ],
            "audio": null,
            "dt": null,
            "fft_freq": null,
            "fft_ampl": null,
            "peak_freq": null,
            "peak_ampl": null,
            "compact": false
        },
        {
            "t": 10.395153045654297,
            "accel": [
                [
                    -0.4,
                    -0.426,
                    10.003
                ]
            ],
            "dist": [
                76.87540179084986
            ],
            "mass": [
                0.0,
                22.5,
                21.67
            ],
            "rpm": [
                5514,
                5585,
                5685,
                5414
            ],
            "audio": null,
            "dt": null,
            "fft_freq": null,
            "fft_ampl": null,
            "peak_freq": null,
            "peak_ampl": null,
            "compact": false
        },
        {
            "t": 10.83019208908081,
            "accel": [
                [
                    -0.56,
                    -2.112,
                    9.309
                ]
            ],
            "dist": [
                76.90787710725668
            ],
            "mass": [
                0.0,
                22.86,
                21.53
            ],
            "rpm": [
                5314,
                5614,
                5571,
                5428
            ],
            "audio": null,
            "dt": null,
            "fft_freq": null,
            "fft_ampl": null,
            "peak_freq": null,
            "peak_ampl": null,
            "compact": false
        },
        {
            "t": 11.28420901298523,
            "accel": [
                [
                    -0.32,
                    0.517,
                    10.779
                ]
            ],
            "dist": [
                76.87511824278754
            ],
            "mass": [
                0.0,
                22.74,
                21.73
            ],
            "rpm": [
                5585,
                5571,
                5514,
                5528
            ],
            "audio": null,
            "dt": null,
            "fft_freq": null,
            "fft_ampl": null,
            "peak_freq": null,
            "peak_ampl": null,
            "compact": false
        },
        {
            "t": 11.7530038356781,
            "accel": [
                [
                    -0.22,
                    -0.407,
                    10.961
                ]
            ],
            "dist": [
                76.88893876854871
            ],
            "mass": [
                0.0,
                22.26,
                21.94
            ],
            "rpm": [
                5585,
                5657,
                5657,
                5428
            ],
            "audio": null,
            "dt": null,
            "fft_freq": null,
            "fft_ampl": null,
            "peak_freq": null,
            "peak_ampl": null,
            "compact": false
        },
        {
            "t": 12.190934896469116,
            "accel": [
                [
                    1.9,
                    0.555,
                    11.569
                ]
            ],
            "dist": [
                76.89397120482664
            ],
            "mass": [
                0.0,
                22.64,
                21.69
            ],
            "rpm": [
                5628,
                5714,
                5642,
                5585
            ],
            "audio": null,
            "dt": null,
            "fft_freq": null,
            "fft_ampl": null,
            "peak_freq": null,
            "peak_ampl": null,
            "compact": false
        },
        {
            "t": 12.60484790802002,
            "accel": [
                [
                    1.6,
                    1.657,
                    9.404
                ]
            ],
            "dist": [
                76.88887230562787
            ],
            "mass": [
                0.0,
                22.58,
                21.7
            ],
            "rpm": [
                5485,
                5514,
                5514,
                5514
            ],
            "audio": null,
            "dt": null,
            "fft_freq": null,
            "fft_ampl": null,
            "peak_freq": null,
            "peak_ampl": null,
            "compact": false
        },
        {
            "t": 13.058069705963135,
            "accel": [
                [
                    2.92,
                    0.263,
                    11.325
                ]
            ],
            "dist": [
                76.88893016325322
            ],
            "mass": [
                0.0,
                22.08,
                21.98
            ],
            "rpm": [
                5528,
                5671,
                5571,
                5671
            ],
            "audio": null,
            "dt": null,
            "fft_freq": null,
            "fft_ampl": null,
            "peak_freq": null,
            "peak_ampl": null,
            "compact": false
        },
        {
            "t": 13.509884119033813,
            "accel": [
                [
                    1.7,
                    2.983,
                    10.104
                ]
            ],
            "dist": [
                76.87604878787837
            ],
            "mass": [
                0.0,
                22.15,
                21.94
            ],
            "rpm": [
                5600,
                5528,
                5571,
                5614
            ],
            "audio": null,
            "dt": null,
            "fft_freq": null,
            "fft_ampl": null,
            "peak_freq": null,
            "peak_ampl": null,
            "compact": false
        },
        {
            "t": 13.970776557922363,
            "accel": [
                [
                    -0.66,
                    -1.815,
                    9.558
                ]
            ],
            "dist": [
                76.8755095500379
            ],
            "mass": [
                0.0,
                22.18,
                21.78
            ],
            "rpm": [
                5642,
                5642,
                5642,
                5585
            ],
            "audio": null,
            "dt": null,
            "fft_freq": null,
            "fft_ampl": null,
            "peak_freq": null,
            "peak_ampl": null,
            "compact": false
        },
        {
            "t": 14.402414083480835,
            "accel": [
                [
                    -0.21,
                    -2.389,
                    10.534
                ]
            ],
            "dist": [
                76.87511824278754
            ],
            "mass": [
                0.0,
                22.09,
                21.82
            ],
            "rpm": [
                5571,
                5600,
                5628,
                5600
            ],
            "audio": null,
            "dt": null,
            "fft_freq": null,
            "fft_ampl": null,
            "peak_freq": null,
            "peak_ampl": null,
            "compact": false
        },
        {
            "t": 14.856988191604614,
            "accel": [
                [
                    0.96,
                    -2.025,
                    9.222
                ]
            ],
            "dist": [
                76.89408212635469
            ],
            "mass": [
                0.0,
                21.67,
                22.29
            ],
            "rpm": [
                5628,
                5585,
                5471,
                5685
            ],
            "audio": null,
            "dt": null,
            "fft_freq": null,
            "fft_ampl": null,
            "peak_freq": null,
            "peak_ampl": null,
            "compact": false
        },
        {
            "t": 15.304560422897339,
            "accel": [
                [
                    2.5,
                    -2.715,
                    10.544
                ]
            ],
            "dist": [
                76.89808413436509
            ],
            "mass": [
                0.0,
                22.11,
                21.92
            ],
            "rpm": [
                5785,
                5600,
                5714,
                5542
            ],
            "audio": null,
            "dt": null,
            "fft_freq": null,
            "fft_ampl": null,
            "peak_freq": null,
            "peak_ampl": null,
            "compact": false
        },
        {
            "t": 15.761242389678955,
            "accel": [
                [
                    -1.71,
                    0.158,
                    9.787
                ]
            ],
            "dist": [
                76.80015321241063
            ],
            "mass": [
                0.0,
                21.52,
                22.36
            ],
            "rpm": [
                5642,
                5500,
                5657,
                5500
            ],
            "audio": null,
            "dt": null,
            "fft_freq": null,
            "fft_ampl": null,
            "peak_freq": null,
            "peak_ampl": null,
            "compact": false
        },
        {
            "t": 16.199942350387573,
            "accel": [
                [
                    -2.17,
                    -1.81,
                    9.802
                ]
            ],
            "dist": [
                76.88893016325322
            ],
            "mass": [
                0.0,
                22.01,
                22.01
            ],
            "rpm": [
                5657,
                5571,
                5628,
                5585
            ],
            "audio": null,
            "dt": null,
            "fft_freq": null,
            "fft_ampl": null,
            "peak_freq": null,
            "peak_ampl": null,
            "compact": false
        },
        {
            "t": 16.600465297698975,
            "accel": [
                [
                    2.68,
                    -0.163,
                    10.4
                ]
            ],
            "dist": [
                76.88893016325322
            ],
            "mass": [
                0.0,
                22.17,
                21.72
            ],
            "rpm": [
                5585,
                5642,
                5528,
                5614
            ],
            "audio": null,
            "dt": null,
            "fft_freq": null,
            "fft_ampl": null,
            "peak_freq": null,
            "peak_ampl": null,
            "compact": false
        },
        {
            "t": 17.05384349822998,
            "accel": [
                [
                    -1.9,
                    0.072,
                    9.816
                ]
            ],
            "dist": [
                76.91239252395437
            ],
            "mass": [
                0.0,
                22.24,
                21.93
            ],
            "rpm": [
                5742,
                5500,
                5528,
                5585
            ],
            "audio": null,
            "dt": null,
            "fft_freq": null,
            "fft_ampl": null,
            "peak_freq": null,
            "peak_ampl": null,
            "compact": false
        },
        {
            "t": 17.51561737060547,
            "accel": [
                [
                    1.13,
                    0.057,
                    10.199
                ]
            ],
            "dist": [
                76.89792511540561
            ],
            "mass": [
                0.0,
                22.13,
                22.0
            ],
            "rpm": [
                5428,
                5414,
                5557,
                5557
            ],
            "audio": null,
            "dt": null,
            "fft_freq": null,
            "fft_ampl": null,
            "peak_freq": null,
            "peak_ampl": null,
            "compact": false
        },
        {
            "t": 17.94179058074951,
            "accel": [
                [
                    -1.45,
                    -0.407,
                    9.51
                ]
            ],
            "dist": [
                76.89786277364011
            ],
            "mass": [
                0.0,
                21.74,
                22.46
            ],
            "rpm": [
                5600,
                5614,
                5442,
                5571
            ],
            "audio": null,
            "dt": null,
            "fft_freq": null,
            "fft_ampl": null,
            "peak_freq": null,
            "peak_ampl": null,
            "compact": false
        },
        {
            "t": 18.401422023773193,
            "accel": [
                [
                    -2.05,
                    0.354,
                    9.61
                ]
            ],
            "dist": [
                76.9117591601929
            ],
            "mass": [
                0.0,
                22.17,
                22.44
            ],
            "rpm": [
                5557,
                5485,
                5628,
                5400
            ],
            "audio": null,
            "dt": null,
            "fft_freq": null,
            "fft_ampl": null,
            "peak_freq": null,
            "peak_ampl": null,
            "compact": false
        },
        {
            "t": 18.85405921936035,
            "accel": [
                [
                    3.25,
                    0.939,
                    10.19
                ]
            ],
            "dist": [
                76.88893016325322
            ],
            "mass": [
                0.0,
                21.96,
                22.35
            ],
            "rpm": [
                5457,
                5614,
                5671,
                5642
            ],
            "audio": null,
            "dt": null,
            "fft_freq": null,
            "fft_ampl": null,
            "peak_freq": null,
            "peak_ampl": null,
            "compact": false
        },
        {
            "t": 19.29957342147827,
            "accel": [
                [
                    0.63,
                    -2.217,
                    10.238
                ]
            ],
            "dist": [
                76.8074774025024
            ],
            "mass": [
                0.0,
                22.5,
                22.1
            ],
            "rpm": [
                5728,
                5585,
                5528,
                5600
            ],
            "audio": null,
            "dt": null,
            "fft_freq": null,
            "fft_ampl": null,
            "peak_freq": null,
            "peak_ampl": null,
            "compact": false
        },
        {
            "t": 19.808430910110474,
            "accel": [
                [
                    0.15,
                    0.646,
                    9.251
                ]
            ],
            "dist": [
                76.87511824278754
            ],
            "mass": [
                0.0,
                21.81,
                22.44
            ],
            "rpm": [
                5514,
                5571,
                5714,
                5585
            ],
            "audio": null,
            "dt": null,
            "fft_freq": null,
            "fft_ampl": null,
            "peak_freq": null,
            "peak_ampl": null,
            "compact": false
        },
        {
            "t": 20.251155614852905,
            "accel": [
                [
                    0.42,
                    1.81,
                    10.898
                ]
            ],
            "dist": [
                76.88929241288744
            ],
            "mass": [
                0.0,
                21.96,
                22.14
            ],
            "rpm": [
                5585,
                5671,
                5571,
                5685
            ],
            "audio": null,
            "dt": null,
            "fft_freq": null,
            "fft_ampl": null,
            "peak_freq": null,
            "peak_ampl": null,
            "compact": false
        },
        {
            "t": 20.70781135559082,
            "accel": [
                [
                    -1.56,
                    0.474,
                    11.545
                ]
            ],
            "dist": [
                76.88887230562787
            ],
            "mass": [
                0.0,
                22.19,
                22.19
            ],
            "rpm": [
                5342,
                5657,
                5657,
                5400
            ],
            "audio": null,
            "dt": null,
            "fft_freq": null,
            "fft_ampl": null,
            "peak_freq": null,
            "peak_ampl": null,
            "compact": false
        },
        {
            "t": 21.22408938407898,
            "accel": [
                [
                    -1.32,
                    -0.441,
                    9.95
                ]
            ],
            "dist": [
                76.87511824278754
            ],
            "mass": [
                0.0,
                21.97,
                22.68
            ],
            "rpm": [
                5614,
                5642,
                5700,
                5414
            ],
            "audio": null,
            "dt": null,
            "fft_freq": null,
            "fft_ampl": null,
            "peak_freq": null,
            "peak_ampl": null,
            "compact": false
        },
        {
            "t": 21.685560941696167,
            "accel": [
                [
                    0.42,
                    2.37,
                    8.121
                ]
            ],
            "dist": [
                76.88929241288744
            ],
            "mass": [
                0.0,
                21.94,
                22.51
            ],
            "rpm": [
                5642,
                5542,
                5657,
                5657
            ],
            "audio": null,
            "dt": null,
            "fft_freq": null,
            "fft_ampl": null,
            "peak_freq": null,
            "peak_ampl": null,
            "compact": false
        },
        {
            "t": 22.17635703086853,
            "accel": [
                [
                    -1.5,
                    0.378,
                    8.461
                ]
            ],
            "dist": [
                76.89808413436509
            ],
            "mass": [
                0.0,
                22.14,
                22.14
            ],
            "rpm": [
                5471,
                5614,
                5671,
                5471
            ],
            "audio": null,
            "dt": null,
            "fft_freq": null,
            "fft_ampl": null,
            "peak_freq": null,
            "peak_ampl": null,
            "compact": false
        },
        {
            "t": 22.678042888641357,
            "accel": [
                [
                    0.0,
                    -2.375,
                    9.625
                ]
            ],
            "dist": [
                76.90277845770646
            ],
            "mass": [
                0.0,
                22.58,
                21.72
            ],
            "rpm": [
                5528,
                5500,
                5514,
                5471
            ],
            "audio": null,
            "dt": null,
            "fft_freq": null,
            "fft_ampl": null,
            "peak_freq": null,
            "peak_ampl": null,
            "compact": false
        },
        {
            "t": 23.131677389144897,
            "accel": [
                [
                    -2.12,
                    -1.791,
                    8.825
                ]
            ],
            "dist": [
                76.88345952504481
            ],
            "mass": [
                0.0,
                22.01,
                22.19
            ],
            "rpm": [
                5485,
                5514,
                5542,
                5571
            ],
            "audio": null,
            "dt": null,
            "fft_freq": null,
            "fft_ampl": null,
            "peak_freq": null,
            "peak_ampl": null,
            "compact": false
        },
        {
            "t": 23.553433179855347,
            "accel": [
                [
                    0.93,
                    0.192,
                    10.659
                ]
            ],
            "dist": [
                76.88899443716346
            ],
            "mass": [
                0.0,
                21.77,
                22.35
            ],
            "rpm": [
                5628,
                5542,
                5628,
                5400
            ],
            "audio": null,
            "dt": null,
            "fft_freq": null,
            "fft_ampl": null,
            "peak_freq": null,
            "peak_ampl": null,
            "compact": false
        },
        {
            "t": 24.01700496673584,
            "accel": [
                [
                    2.75,
                    -2.442,
                    8.375
                ]
            ],
            "dist": [
                76.88899443716346
            ],
            "mass": [
                0.0,
                21.83,
                22.35
            ],
            "rpm": [
                5628,
                5542,
                5685,
                5542
            ],
            "audio": null,
            "dt": null,
            "fft_freq": null,
            "fft_ampl": null,
            "peak_freq": null,
            "peak_ampl": null,
            "compact": false
        },
        {
            "t": 24.526085138320923,
            "accel": [
                [
                    1.89,
                    2.198,
                    9.333
                ]
            ],
            "dist": [
                76.87604878787837
            ],
            "mass": [
                0.0,
                21.61,
                22.77
            ],
            "rpm": [
                5642,
                5514,
                5600,
                5571
            ],
            "audio": null,
            "dt": null,
            "fft_freq": null,
            "fft_ampl": null,
            "peak_freq": null,
            "peak_ampl": null,
            "compact": false
        },
        {
            "t": 24.946946382522583,
            "accel": [
                [
                    1.02,
                    0.512,
                    8.203
                ]
            ],
            "dist": [
                76.87511824278754
            ],
            "mass": [
                0.0,
                21.59,
                22.65
            ],
            "rpm": [
                5757,
                5442,
                5585,
                5657
            ],
            "audio": null,
            "dt": null,
            "fft_freq": null,
            "fft_ampl": null,
            "peak_freq": null,
            "peak_ampl": null,
            "compact": false
        },
        {
            "t": 25.40950894355774,
            "accel": [
                [
                    2.52,
                    -2.643,
                    10.755
                ]
            ],
            "dist": [
                76.80764747157866
            ],
            "mass": [
                0.0,
                21.87,
                22.49
            ],
            "rpm": [
                5528,
                5442,
                5642,
                5628
            ],
            "audio": null,
            "dt": null,
            "fft_freq": null,
            "fft_ampl": null,
            "peak_freq": null,
            "peak_ampl": null,
            "compact": false
        },
        {
            "t": 25.85210132598877,
            "accel": [
                [
                    -0.97,
                    -0.871,
                    10.918
                ]
            ],
            "dist": [
                76.88893016325322
            ],
            "mass": [
                0.0,
                21.68,
                22.18
            ],
            "rpm": [
                5528,
                5557,
                5685,
                5357
            ],
            "audio": null,
            "dt": null,
            "fft_freq": null,
            "fft_ampl": null,
            "peak_freq": null,
            "peak_ampl": null,
            "compact": false
        },
        {
            "t": 26.309783697128296,
            "accel": [
                [
                    0.48,
                    3.127,
                    10.295
                ]
            ],
            "dist": [
                76.88503134230042
            ],
            "mass": [
                0.0,
                21.17,
                22.7
            ],
            "rpm": [
                5614,
                5657,
                5585,
                5600
            ],
            "audio": null,
            "dt": null,
            "fft_freq": null,
            "fft_ampl": null,
            "peak_freq": null,
            "peak_ampl": null,
            "compact": false
        },
        {
            "t": 26.76232123374939,
            "accel": [
                [
                    0.08,
                    -0.972,
                    10.525
                ]
            ],
            "dist": [
                76.89311303599891
            ],
            "mass": [
                0.0,
                21.75,
                21.96
            ],
            "rpm": [
                5671,
                5571,
                5585,
                5685
            ],
            "audio": null,
            "dt": null,
            "fft_freq": null,
            "fft_ampl": null,
            "peak_freq": null,
            "peak_ampl": null,
            "compact": false
        },
        {
            "t": 27.18999457359314,
            "accel": [
                [
                    -0.76,
                    -0.599,
                    10.324
                ]
            ],
            "dist": [
                76.89808413436509
            ],
            "mass": [
                0.0,
                21.29,
                22.49
            ],
            "rpm": [
                5742,
                5457,
                5428,
                5385
            ],
            "audio": null,
            "dt": null,
            "fft_freq": null,
            "fft_ampl": null,
            "peak_freq": null,
            "peak_ampl": null,
            "compact": false
        },
        {
            "t": 27.631313800811768,
            "accel": [
                [
                    -0.11,
                    -1.279,
                    10.127
                ]
            ],
            "dist": [
                76.88893016325322
            ],
            "mass": [
                0.0,
                21.44,
                22.71
            ],
            "rpm": [
                5700,
                5442,
                5571,
                5500
            ],
            "audio": null,
            "dt": null,
            "fft_freq": null,
            "fft_ampl": null,
            "peak_freq": null,
            "peak_ampl": null,
            "compact": false
        },
        {
            "t": 28.098144054412842,
            "accel": [
                [
                    -5.32,
                    -2.025,
                    8.705
                ]
            ],
            "dist": [
                76.88893016325322
            ],
            "mass": [
                0.0,
                21.24,
                22.67
            ],
            "rpm": [
                5742,
                5657,
                5500,
                5585
            ],
            "audio": null,
            "dt": null,
            "fft_freq": null,
            "fft_ampl": null,
            "peak_freq": null,
            "peak_ampl": null,
            "compact": false
        },
        {
            "t": 28.518951177597046,
            "accel": [
                [
                    -0.24,
                    1.302,
                    10.444
                ]
            ],
            "dist": [
                76.90245553643143
            ],
            "mass": [
                0.0,
                21.49,
                22.8
            ],
            "rpm": [
                5400,
                5557,
                5614,
                5685
            ],
            "audio": null,
            "dt": null,
            "fft_freq": null,
            "fft_ampl": null,
            "peak_freq": null,
            "peak_ampl": null,
            "compact": false
        },
        {
            "t": 28.943862438201904,
            "accel": [
                [
                    0.44,
                    -1.259,
                    10.089
                ]
            ],
            "dist": [
                76.88893016325322
            ],
            "mass": [
                0.0,
                21.42,
                22.55
            ],
            "rpm": [
                5442,
                5614,
                5600,
                5400
            ],
            "audio": null,
            "dt": null,
            "fft_freq": null,
            "fft_ampl": null,
            "peak_freq": null,
            "peak_ampl": null,
            "compact": false
        },
        {
            "t": 29.44744634628296,
            "accel": [
                [
                    -1.07,
                    -2.126,
                    11.411
                ]
            ],
            "dist": [
                76.90352977337831
            ],
            "mass": [
                0.0,
                21.56,
                22.9
            ],
            "rpm": [
                5685,
                5542,
                5528,
                5685
            ],
            "audio": null,
            "dt": null,
            "fft_freq": null,
            "fft_ampl": null,
            "peak_freq": null,
            "peak_ampl": null,
            "compact": false
        },
        {
            "t": 29.90268564224243,
            "accel": [
                [
                    1.2,
                    2.356,
                    10.444
                ]
            ],
            "dist": [
                76.87511824278754
            ],
            "mass": [
                0.0,
                21.46,
                22.54
            ],
            "rpm": [
                5642,
                5571,
                5585,
                5571
            ],
            "audio": null,
            "dt": null,
            "fft_freq": null,
            "fft_ampl": null,
            "peak_freq": null,
            "peak_ampl": null,
            "compact": false
        }
    ]
}