{
    "height": 89,
    "target_rpm": [
        5000.0,
        5000.0,
        5000.0,
        5000.0
    ],
    "timestamp": 1711375918.8860478,
    "platform": "betaflight-2",
    "description": null,
    "compact": false,
    "frames": [
        {
            "t": 0.0,
            "accel": [
                [
                    4.58,
                    10.506,
                    10.4
                ]
            ],
            "dist": [
                90.27361078515416
            ],
            "mass": [
                0.0,
                16.41,
                14.44
            ],
            "rpm": [
                4957,
                4685,
                4842,
                4685
            ],
            "audio": null,
            "dt": null,
            "fft_freq": null,
            "fft_ampl": null,
            "peak_freq": null,
            "peak_ampl": null,
            "compact": false
        },
        {
            "t": 0.5022449493408203,
            "accel": [
                [
                    -9.7,
                    -1.973,
                    7.901
                ]
            ],
            "dist": [
                90.29788282888822
            ],
            "mass": [
                0.0,
                16.43,
                14.62
            ],
            "rpm": [
                4842,
                4685,
                4757,
                4614
            ],
            "audio": null,
            "dt": null,
            "fft_freq": null,
            "fft_ampl": null,
            "peak_freq": null,
            "peak_ampl": null,
            "compact": false
        },
        {
            "t": 0.9910094738006592,
            "accel": [
                [
                    3.23,
                    9.266,
                    11.578
                ]
            ],
            "dist": [
                90.2977436391359
            ],
            "mass": [
                0.0,
                16.23,
                14.62
            ],
            "rpm": [
                4814,
                4700,
                4814,
                4628
            ],
            "audio": null,
            "dt": null,
            "fft_freq": null,
            "fft_ampl": null,
            "peak_freq": null,
            "peak_ampl": null,
            "compact": false
        },
        {
            "t": 1.4167301654815674,
            "accel": [
                [
                    0.46,
                    -7.13,
                    11.511
                ]
            ],
            "dist": [
                90.27361078515416
            ],
            "mass": [
                0.0,
                16.18,
                15.01
            ],
            "rpm": [
                4771,
                4657,
                4757,
                4771
            ],
            "audio": null,
            "dt": null,
            "fft_freq": null,
            "fft_ampl": null,
            "peak_freq": null,
            "peak_ampl": null,
            "compact": false
        },
        {
            "t": 1.9563407897949219,
            "accel": [
                [
                    -5.52,
                    -15.189,
                    10.209
                ]
            ],
            "dist": [
                90.26713768199517
            ],
            "mass": [
                0.0,
                16.41,
                14.8
            ],
            "rpm": [
                4785,
                4657,
                4728,
                4600
            ],
            "audio": null,
            "dt": null,
            "fft_freq": null,
            "fft_ampl": null,
            "peak_freq": null,
            "peak_ampl": null,
            "compact": false
        },
        {
            "t": 2.4570603370666504,
            "accel": [
                [
                    6.29,
                    11.08,
                    7.321
                ]
            ],
            "dist": [
                90.27361078515416
            ],
            "mass": [
                0.0,
                16.27,
                14.61
            ],
            "rpm": [
                4957,
                4685,
                4714,
                4671
            ],
            "audio": null,
            "dt": null,
            "fft_freq": null,
            "fft_ampl": null,
            "peak_freq": null,
            "peak_ampl": null,
            "compact": false
        },
        {
            "t": 2.9016566276550293,
            "accel": [
                [
                    2.61,
                    5.741,
                    10.046
                ]
            ],
            "dist": [
                90.29788282888822
            ],
            "mass": [
                0.0,
                16.22,
                14.71
            ],
            "rpm": [
                4842,
                4742,
                4757,
                4614
            ],
            "audio": null,
            "dt": null,
            "fft_freq": null,
            "fft_ampl": null,
            "peak_freq": null,
            "peak_ampl": null,
            "compact": false
        },
        {
            "t": 3.408435821533203,
            "accel": [
                [
                    3.62,
                    4.745,
                    11.435
                ]
            ],
            "dist": [
                90.27361078515416
            ],
            "mass": [
                0.0,
                16.12,
                14.89
            ],
            "rpm": [
                4685,
                4771,
                4842,
                4800
            ],
            "audio": null,
            "dt": null,
            "fft_freq": null,
            "fft_ampl": null,
            "peak_freq": null,
            "peak_ampl": null,
            "compact": false
        },
        {
            "t": 3.841010093688965,
            "accel": [
                [
                    10.1,
                    2.442,
                    11.842
                ]
            ],
            "dist": [
                90.2977436391359
            ],
            "mass": [
                0.0,
                16.03,
                14.86
            ],
            "rpm": [
                4800,
                4657,
                4757,
                4614
            ],
            "audio": null,
            "dt": null,
            "fft_freq": null,
            "fft_ampl": null,
            "peak_freq": null,
            "peak_ampl": null,
            "compact": false
        },
        {
            "t": 4.283181667327881,
            "accel": [
                [
                    -3.74,
                    3.802,
                    9.074
                ]
            ],
            "dist": [
                90.27361078515416
            ],
            "mass": [
                0.0,
                16.13,
                14.51
            ],
            "rpm": [
                4657,
                4842,
                4800,
                4757
            ],
            "audio": null,
            "dt": null,
            "fft_freq": null,
            "fft_ampl": null,
            "peak_freq": null,
            "peak_ampl": null,
            "compact": false
        },
        {
            "t": 4.813266754150391,
            "accel": [
                [
                    -1.95,
                    2.241,
                    9.079
                ]
            ],
            "dist": [
                90.27361078515416
            ],
            "mass": [
                0.0,
                16.35,
                14.62
            ],
            "rpm": [
                4857,
                4714,
                4800,
                4642
            ],
            "audio": null,
            "dt": null,
            "fft_freq": null,
            "fft_ampl": null,
            "peak_freq": null,
            "peak_ampl": null,
            "compact": false
        },
        {
            "t": 5.277872562408447,
            "accel": [
                [
                    0.65,
                    -3.266,
                    11.832
                ]
            ],
            "dist": [
                90.29788282888822
            ],
            "mass": [
                0.0,
                16.8,
                14.48
            ],
            "rpm": [
                4814,
                4771,
                4800,
                4614
            ],
            "audio": null,
            "dt": null,
            "fft_freq": null,
            "fft_ampl": null,
            "peak_freq": null,
            "peak_ampl": null,
            "compact": false
        },
        {
            "t": 5.743431091308594,
            "accel": [
                [
                    -0.33,
                    7.293,
                    8.078
                ]
            ],
            "dist": [
                90.2977436391359
            ],
            "mass": [
                0.0,
                16.38,
                14.84
            ],
            "rpm": [
                4785,
                4814,
                4685,
                4585
            ],
            "audio": null,
            "dt": null,
            "fft_freq": null,
            "fft_ampl": null,
            "peak_freq": null,
            "peak_ampl": null,
            "compact": false
        },
        {
            "t": 6.259461879730225,
            "accel": [
                [
                    4.12,
                    5.775,
                    10.175
                ]
            ],
            "dist": [
                90.27361078515416
            ],
            "mass": [
                0.0,
                16.36,
                14.77
            ],
            "rpm": [
                4714,
                4714,
                4828,
                4685
            ],
            "audio": null,
            "dt": null,
            "fft_freq": null,
            "fft_ampl": null,
            "peak_freq": null,
            "peak_ampl": null,
            "compact": false
        },
        {
            "t": 6.783130884170532,
            "accel": [
                [
                    -1.93,
                    8.38,
                    9.744
                ]
            ],
            "dist": [
                90.2977436391359
            ],
            "mass": [
                0.0,
                16.36,
                14.67
            ],
            "rpm": [
                4800,
                4728,
                4771,
                4600
            ],
            "audio": null,
            "dt": null,
            "fft_freq": null,
            "fft_ampl": null,
            "peak_freq": null,
            "peak_ampl": null,
            "compact": false
        },
        {
            "t": 7.193321943283081,
            "accel": [
                [
                    0.73,
                    -0.795,
                    9.404
                ]
            ],
            "dist": [
                90.27361078515416
            ],
            "mass": [
                0.0,
                16.33,
                14.6
            ],
            "rpm": [
                4757,
                4642,
                4714,
                4714
            ],
            "audio": null,
            "dt": null,
            "fft_freq": null,
            "fft_ampl": null,
            "peak_freq": null,
            "peak_ampl": null,
            "compact": false
        },
        {
            "t": 7.6344804763793945,
            "accel": [
                [
                    0.27,
                    -2.974,
                    7.728
                ]
            ],
            "dist": [
                90.2977436391359
            ],
            "mass": [
                0.0,
                16.41,
                14.65
            ],
            "rpm": [
                4900,
                4842,
                4728,
                4657
            ],
            "audio": null,
            "dt": null,
            "fft_freq": null,
            "fft_ampl": null,
            "peak_freq": null,
            "peak_ampl": null,
            "compact": false
        },
        {
            "t": 8.10278582572937,
            "accel": [
                [
                    -5.3,
                    4.209,
                    10.611
                ]
            ],
            "dist": [
                90.29788282888822
            ],
            "mass": [
                0.0,
                15.97,
                14.84
            ],
            "rpm": [
                4885,
                4785,
                4828,
                4714
            ],
            "audio": null,
            "dt": null,
            "fft_freq": null,
            "fft_ampl": null,
            "peak_freq": null,
            "peak_ampl": null,
            "compact": false
        },
        {
            "t": 8.574405193328857,
            "accel": [
                [
                    6.7,
                    7.12,
                    9.84
                ]
            ],
            "dist": [
                90.27361078515416
            ],
            "mass": [
                0.0,
                15.91,
                14.93
            ],
            "rpm": [
                4785,
                4671,
                4800,
                4614
            ],
            "audio": null,
            "dt": null,
            "fft_freq": null,
            "fft_ampl": null,
            "peak_freq": null,
            "peak_ampl": null,
            "compact": false
        },
        {
            "t": 9.040703058242798,
            "accel": [
                [
                    -7.33,
                    -4.707,
                    8.442
                ]
            ],
            "dist": [
                90.2977436391359
            ],
            "mass": [
                0.0,
                16.0,
                14.79
            ],
            "rpm": [
                4657,
                4828,
                4771,
                4657
            ],
            "audio": null,
            "dt": null,
            "fft_freq": null,
            "fft_ampl": null,
            "peak_freq": null,
            "peak_ampl": null,
            "compact": false
        },
        {
            "t": 9.467488527297974,
            "accel": [
                [
                    2.04,
                    -3.342,
                    12.263
                ]
            ],
            "dist": [
                90.2977436391359
            ],
            "mass": [
                0.0,
                15.87,
                14.93
            ],
            "rpm": [
                4757,
                4800,
                4785,
                4671
            ],
            "audio": null,
            "dt": null,
            "fft_freq": null,
            "fft_ampl": null,
            "peak_freq": null,
            "peak_ampl": null,
            "compact": false
        },
        {
            "t": 9.962965250015259,
            "accel": [
                [
                    -2.37,
                    -1.192,
                    10.18
                ]
            ],
            "dist": [
                90.29788282888822
            ],
            "mass": [
                0.0,
                15.48,
                14.98
            ],
            "rpm": [
                4942,
                4771,
                4828,
                4628
            ],
            "audio": null,
            "dt": null,
            "fft_freq": null,
            "fft_ampl": null,
            "peak_freq": null,
            "peak_ampl": null,
            "compact": false
        },
        {
            "t": 10.442452907562256,
            "accel": [
                [
                    -3.25,
                    -14.514,
                    10.52
                ]
            ],
            "dist": [
                90.2977436391359
            ],
            "mass": [
                0.0,
                15.62,
                14.8
            ],
            "rpm": [
                5014,
                4800,
                4742,
                4728
            ],
            "audio": null,
            "dt": null,
            "fft_freq": null,
            "fft_ampl": null,
            "peak_freq": null,
            "peak_ampl": null,
            "compact": false
        },
        {
            "t": 10.947269916534424,
            "accel": [
                [
                    8.13,
                    2.48,
                    9.601
                ]
            ],
            "dist": [
                90.22659698205649
            ],
            "mass": [
                0.0,
                15.85,
                14.99
            ],
            "rpm": [
                4914,
                4714,
                4728,
                4700
            ],
            "audio": null,
            "dt": null,
            "fft_freq": null,
            "fft_ampl": null,
            "peak_freq": null,
            "peak_ampl": null,
            "compact": false
        },
        {
            "t": 11.44827127456665,
            "accel": [
                [
                    -2.38,
                    -2.298,
                    7.207
                ]
            ],
            "dist": [
                90.2977436391359
            ],
            "mass": [
                0.0,
                15.87,
                14.89
            ],
            "rpm": [
                4785,
                4714,
                4700,
                4614
            ],
            "audio": null,
            "dt": null,
            "fft_freq": null,
            "fft_ampl": null,
            "peak_freq": null,
            "peak_ampl": null,
            "compact": false
        },
        {
            "t": 11.897444725036621,
            "accel": [
                [
                    2.78,
                    12.962,
                    9.131
                ]
            ],
            "dist": [
                90.29788282888822
            ],
            "mass": [
                0.0,
                15.71,
                15.04
            ],
            "rpm": [
                4742,
                4700,
                4885,
                4600
            ],
            "audio": null,
            "dt": null,
            "fft_freq": null,
            "fft_ampl": null,
            "peak_freq": null,
            "peak_ampl": null,
            "compact": false
        },
        {
            "t": 12.362855195999146,
            "accel": [
                [
                    -15.5,
                    -1.053,
                    9.366
                ]
            ],
            "dist": [
                90.29788282888822
            ],
            "mass": [
                0.0,
                16.07,
                14.72
            ],
            "rpm": [
                4914,
                4685,
                4828,
                4785
            ],
            "audio": null,
            "dt": null,
            "fft_freq": null,
            "fft_ampl": null,
            "peak_freq": null,
            "peak_ampl": null,
            "compact": false
        },
        {
            "t": 12.851603031158447,
            "accel": [
                [
                    3.3,
                    -2.054,
                    10.309
                ]
            ],
            "dist": [
                90.27361078515416
            ],
            "mass": [
                0.0,
                15.8,
                14.94
            ],
            "rpm": [
                4857,
                4657,
                4800,
                4528
            ],
            "audio": null,
            "dt": null,
            "fft_freq": null,
            "fft_ampl": null,
            "peak_freq": null,
            "peak_ampl": null,
            "compact": false
        },
        {
            "t": 13.33937931060791,
            "accel": [
                [
                    2.83,
                    -0.464,
                    11.1
                ]
            ],
            "dist": [
                90.2977436391359
            ],
            "mass": [
                0.0,
                15.7,
                14.88
            ],
            "rpm": [
                4885,
                4800,
                4642,
                4642
            ],
            "audio": null,
            "dt": null,
            "fft_freq": null,
            "fft_ampl": null,
            "peak_freq": null,
            "peak_ampl": null,
            "compact": false
        },
        {
            "t": 13.825416088104248,
            "accel": [
                [
                    -8.06,
                    -3.5,
                    9.596
                ]
            ],
            "dist": [
                90.2977436391359
            ],
            "mass": [
                0.0,
                15.93,
                15.11
            ],
            "rpm": [
                5071,
                4642,
                4657,
                4757
            ],
            "audio": null,
            "dt": null,
            "fft_freq": null,
            "fft_ampl": null,
            "peak_freq": null,
            "peak_ampl": null,
            "compact": false
        },
        {
            "t": 14.291782855987549,
            "accel": [
                [
                    -11.09,
                    -0.177,
                    9.553
                ]
            ],
            "dist": [
                90.29788282888822
            ],
            "mass": [
                0.0,
                15.83,
                15.05
            ],
            "rpm": [
                4842,
                4600,
                4828,
                4614
            ],
            "audio": null,
            "dt": null,
            "fft_freq": null,
            "fft_ampl": null,
            "peak_freq": null,
            "peak_ampl": null,
            "compact": false
        },
        {
            "t": 14.766637563705444,
            "accel": [
                [
                    9.03,
                    0.584,
                    11.55
                ]
            ],
            "dist": [
                90.2977436391359
            ],
            "mass": [
                0.0,
                16.08,
                15.19
            ],
            "rpm": [
                4857,
                4800,
                4600,
                4642
            ],
            "audio": null,
            "dt": null,
            "fft_freq": null,
            "fft_ampl": null,
            "peak_freq": null,
            "peak_ampl": null,
            "compact": false
        },
        {
            "t": 15.309283256530762,
            "accel": [
                [
                    7.65,
                    1.288,
                    13.364
                ]
            ],
            "dist": [
                90.2977436391359
            ],
            "mass": [
                0.0,
                16.16,
                15.05
            ],
            "rpm": [
                4828,
                4800,
                4700,
                4571
            ],
            "audio": null,
            "dt": null,
            "fft_freq": null,
            "fft_ampl": null,
            "peak_freq": null,
            "peak_ampl": null,
            "compact": false
        },
        {
            "t": 15.799463987350464,
            "accel": [
                [
                    4.98,
                    13.115,
                    9.874
                ]
            ],
            "dist": [
                90.27361078515416
            ],
            "mass": [
                0.0,
                16.27,
                15.0
            ],
            "rpm": [
                4928,
                4728,
                4771,
                4714
            ],
            "audio": null,
            "dt": null,
            "fft_freq": null,
            "fft_ampl": null,
            "peak_freq": null,
            "peak_ampl": null,
            "compact": false
        },
        {
            "t": 16.28597140312195,
            "accel": [
                [
                    1.21,
                    -3.74,
                    9.103
                ]
            ],
            "dist": [
                90.29788282888822
            ],
            "mass": [
                0.0,
                16.12,
                15.18
            ],
            "rpm": [
                4814,
                4814,
                4685,
                4585
            ],
            "audio": null,
            "dt": null,
            "fft_freq": null,
            "fft_ampl": null,
            "peak_freq": null,
            "peak_ampl": null,
            "compact": false
        },
        {
            "t": 16.7505304813385,
            "accel": [
                [
                    3.9,
                    -8.226,
                    11.693
                ]
            ],
            "dist": [
                90.2977436391359
            ],
            "mass": [
                0.0,
                15.98,
                15.16
            ],
            "rpm": [
                4785,
                4871,
                4771,
                4785
            ],
            "audio": null,
            "dt": null,
            "fft_freq": null,
            "fft_ampl": null,
            "peak_freq": null,
            "peak_ampl": null,
            "compact": false
        },
        {
            "t": 17.224955081939697,
            "accel": [
                [
                    -4.21,
                    6.555,
                    8.921
                ]
            ],
            "dist": [
                90.27361078515416
            ],
            "mass": [
                0.0,
                16.24,
                15.12
            ],
            "rpm": [
                4928,
                4771,
                4657,
                4714
            ],
            "audio": null,
            "dt": null,
            "fft_freq": null,
            "fft_ampl": null,
            "peak_freq": null,
            "peak_ampl": null,
            "compact": false
        },
        {
            "t": 17.698054552078247,
            "accel": [
                [
                    2.78,
                    10.894,
                    11.578
                ]
            ],
            "dist": [
                90.29788282888822
            ],
            "mass": [
                0.0,
                16.16,
                15.08
            ],
            "rpm": [
                4814,
                4614,
                4728,
                4657
            ],
            "audio": null,
            "dt": null,
            "fft_freq": null,
            "fft_ampl": null,
            "peak_freq": null,
            "peak_ampl": null,
            "compact": false
        },
        {
            "t": 18.13832664489746,
            "accel": [
                [
                    11.33,
                    6.996,
                    10.951
                ]
            ],
            "dist": [
                90.27361078515416
            ],
            "mass": [
                0.0,
                16.14,
                15.12
            ],
            "rpm": [
                4700,
                4657,
                4800,
                4785
            ],
            "audio": null,
            "dt": null,
            "fft_freq": null,
            "fft_ampl": null,
            "peak_freq": null,
            "peak_ampl": null,
            "compact": false
        },
        {
            "t": 18.63932752609253,
            "accel": [
                [
                    12.45,
                    5.827,
                    11.799
                ]
            ],
            "dist": [
                90.2977436391359
            ],
            "mass": [
                0.0,
                16.09,
                15.24
            ],
            "rpm": [
                4814,
                4700,
                4642,
                4785
            ],
            "audio": null,
            "dt": null,
            "fft_freq": null,
            "fft_ampl": null,
            "peak_freq": null,
            "peak_ampl": null,
            "compact": false
        },
        {
            "t": 19.148467302322388,
            "accel": [
                [
                    -6.03,
                    -0.819,
                    9.151
                ]
            ],
            "dist": [
                90.29788282888822
            ],
            "mass": [
                0.0,
                15.81,
                15.27
            ],
            "rpm": [
                4842,
                4642,
                4757,
                4757
            ],
            "audio": null,
            "dt": null,
            "fft_freq": null,
            "fft_ampl": null,
            "peak_freq": null,
            "peak_ampl": null,
            "compact": false
        },
        {
            "t": 19.58094096183777,
            "accel": [
                [
                    7.32,
                    10.654,
                    8.471
                ]
            ],
            "dist": [
                90.2977436391359
            ],
            "mass": [
                0.0,
                16.1,
                15.18
            ],
            "rpm": [
                4885,
                4757,
                4642,
                4685
            ],
            "audio": null,
            "dt": null,
            "fft_freq": null,
            "fft_ampl": null,
            "peak_freq": null,
            "peak_ampl": null,
            "compact": false
        },
        {
            "t": 20.141337394714355,
            "accel": [
                [
                    -4.21,
                    12.589,
                    9.874
                ]
            ],
            "dist": [
                90.2977436391359
            ],
            "mass": [
                0.0,
                15.7,
                15.65
            ],
            "rpm": [
                4914,
                4771,
                4657,
                4628
            ],
            "audio": null,
            "dt": null,
            "fft_freq": null,
            "fft_ampl": null,
            "peak_freq": null,
            "peak_ampl": null,
            "compact": false
        },
        {
            "t": 20.612807512283325,
            "accel": [
                [
                    6.11,
                    -3.73,
                    11.066
                ]
            ],
            "dist": [
                90.27361078515416
            ],
            "mass": [
                0.0,
                15.95,
                15.6
            ],
            "rpm": [
                4871,
                4800,
                4585,
                4657
            ],
            "audio": null,
            "dt": null,
            "fft_freq": null,
            "fft_ampl": null,
            "peak_freq": null,
            "peak_ampl": null,
            "compact": false
        },
        {
            "t": 21.136872053146362,
            "accel": [
                [
                    -8.34,
                    10.836,
                    10.319
                ]
            ],
            "dist": [
                90.29788282888822
            ],
            "mass": [
                0.0,
                16.35,
                15.33
            ],
            "rpm": [
                4985,
                4814,
                4642,
                4614
            ],
            "audio": null,
            "dt": null,
            "fft_freq": null,
            "fft_ampl": null,
            "peak_freq": null,
            "peak_ampl": null,
            "compact": false
        },
        {
            "t": 21.62331748008728,
            "accel": [
                [
                    2.59,
                    -1.925,
                    12.929
                ]
            ],
            "dist": [
                90.27361078515416
            ],
            "mass": [
                0.0,
                16.26,
                15.47
            ],
            "rpm": [
                4885,
                4785,
                4757,
                4657
            ],
            "audio": null,
            "dt": null,
            "fft_freq": null,
            "fft_ampl": null,
            "peak_freq": null,
            "peak_ampl": null,
            "compact": false
        },
        {
            "t": 22.098588943481445,
            "accel": [
                [
                    -6.96,
                    -2.26,
                    9.826
                ]
            ],
            "dist": [
                90.27361078515416
            ],
            "mass": [
                0.0,
                16.04,
                15.32
            ],
            "rpm": [
                4914,
                4757,
                4657,
                4542
            ],
            "audio": null,
            "dt": null,
            "fft_freq": null,
            "fft_ampl": null,
            "peak_freq": null,
            "peak_ampl": null,
            "compact": false
        },
        {
            "t": 22.59030294418335,
            "accel": [
                [
                    -6.19,
                    -10.171,
                    10.865
                ]
            ],
            "dist": [
                90.27361078515416
            ],
            "mass": [
                0.0,
                16.01,
                15.27
            ],
            "rpm": [
                4842,
                4671,
                4742,
                4685
            ],
            "audio": null,
            "dt": null,
            "fft_freq": null,
            "fft_ampl": null,
            "peak_freq": null,
            "peak_ampl": null,
            "compact": false
        },
        {
            "t": 23.12470769882202,
            "accel": [
                [
                    -4.18,
                    -8.897,
                    9.562
                ]
            ],
            "dist": [
                90.27361078515416
            ],
            "mass": [
                0.0,
                16.04,
                15.41
            ],
            "rpm": [
                4914,
                4842,
                4700,
                4600
            ],
            "audio": null,
            "dt": null,
            "fft_freq": null,
            "fft_ampl": null,
            "peak_freq": null,
            "peak_ampl": null,
            "compact": false
        },
        {
            "t": 23.585639715194702,
            "accel": [
                [
                    3.99,
                    15.27,
                    10.008
                ]
            ],
            "dist": [
                90.29788282888822
            ],
            "mass": [
                0.0,
                15.83,
                15.02
            ],
            "rpm": [
                4771,
                4800,
                4785,
                4642
            ],
            "audio": null,
            "dt": null,
            "fft_freq": null,
            "fft_ampl": null,
            "peak_freq": null,
            "peak_ampl": null,
            "compact": false
        },
        {
            "t": 24.101269483566284,
            "accel": [
                [
                    4.63,
                    -0.886,
                    10.673
                ]
            ],
            "dist": [
                90.29788282888822
            ],
            "mass": [
                0.0,
                15.55,
                15.45
            ],
            "rpm": [
                4757,
                4685,
                4742,
                4685
            ],
            "audio": null,
            "dt": null,
            "fft_freq": null,
            "fft_ampl": null,
            "peak_freq": null,
            "peak_ampl": null,
            "compact": false
        },
        {
            "t": 24.544799327850342,
            "accel": [
                [
                    -13.61,
                    -2.322,
                    8.375
                ]
            ],
            "dist": [
                90.2977436391359
            ],
            "mass": [
                0.0,
                15.57,
                15.27
            ],
            "rpm": [
                4885,
                4800,
                4571,
                4700
            ],
            "audio": null,
            "dt": null,
            "fft_freq": null,
            "fft_ampl": null,
            "peak_freq": null,
            "peak_ampl": null,
            "compact": false
        },
        {
            "t": 25.005796432495117,
            "accel": [
                [
                    8.6,
                    -2.14,
                    10.199
                ]
            ],
            "dist": [
                90.29733019076102
            ],
            "mass": [
                0.0,
                15.75,
                14.98
            ],
            "rpm": [
                4842,
                4714,
                4642,
                4614
            ],
            "audio": null,
            "dt": null,
            "fft_freq": null,
            "fft_ampl": null,
            "peak_freq": null,
            "peak_ampl": null,
            "compact": false
        },
        {
            "t": 25.408607959747314,
            "accel": [
                [
                    -0.85,
                    -0.603,
                    9.131
                ]
            ],
            "dist": [
                90.2977436391359
            ],
            "mass": [
                0.0,
                15.43,
                15.32
            ],
            "rpm": [
                4785,
                4857,
                4742,
                4700
            ],
            "audio": null,
            "dt": null,
            "fft_freq": null,
            "fft_ampl": null,
            "peak_freq": null,
            "peak_ampl": null,
            "compact": false
        },
        {
            "t": 25.880345106124878,
            "accel": [
                [
                    6.22,
                    5.966,
                    10.094
                ]
            ],
            "dist": [
                90.27361078515416
            ],
            "mass": [
                0.0,
                15.67,
                15.42
            ],
            "rpm": [
                4914,
                4742,
                4585,
                4671
            ],
            "audio": null,
            "dt": null,
            "fft_freq": null,
            "fft_ampl": null,
            "peak_freq": null,
            "peak_ampl": null,
            "compact": false
        },
        {
            "t": 26.322460651397705,
            "accel": [
                [
                    8.07,
                    14.523,
                    9.404
                ]
            ],
            "dist": [
                90.29788282888822
            ],
            "mass": [
                0.0,
                15.98,
                15.36
            ],
            "rpm": [
                4900,
                4771,
                4614,
                4585
            ],
            "audio": null,
            "dt": null,
            "fft_freq": null,
            "fft_ampl": null,
            "peak_freq": null,
            "peak_ampl": null,
            "compact": false
        },
        {
            "t": 26.791871070861816,
            "accel": [
                [
                    1.82,
                    6.756,
                    11.497
                ]
            ],
            "dist": [
                90.29787128099557
            ],
            "mass": [
                0.0,
                16.15,
                15.12
            ],
            "rpm": [
                4885,
                4700,
                4714,
                4614
            ],
            "audio": null,
            "dt": null,
            "fft_freq": null,
            "fft_ampl": null,
            "peak_freq": null,
            "peak_ampl": null,
            "compact": false
        },
        {
            "t": 27.24401092529297,
            "accel": [
                [
                    4.3,
                    0.287,
                    9.989
                ]
            ],
            "dist": [
                90.2977436391359
            ],
            "mass": [
                0.0,
                15.89,
                15.35
            ],
            "rpm": [
                4885,
                4642,
                4785,
                4714
            ],
            "audio": null,
            "dt": null,
            "fft_freq": null,
            "fft_ampl": null,
            "peak_freq": null,
            "peak_ampl": null,
            "compact": false
        },
        {
            "t": 27.704085111618042,
            "accel": [
                [
                    -5.94,
                    5.31,
                    7.494
                ]
            ],
            "dist": [
                90.29788282888822
            ],
            "mass": [
                0.0,
                15.69,
                15.41
            ],
            "rpm": [
                4828,
                4671,
                4828,
                4642
            ],
            "audio": null,
            "dt": null,
            "fft_freq": null,
            "fft_ampl": null,
            "peak_freq": null,
            "peak_ampl": null,
            "compact": false
        },
        {
            "t": 28.18514633178711,
            "accel": [
                [
                    -6.5,
                    3.146,
                    9.979
                ]
            ],
            "dist": [
                90.27361078515416
            ],
            "mass": [
                0.0,
                16.4,
                14.95
            ],
            "rpm": [
                4857,
                4800,
                4685,
                4800
            ],
            "audio": null,
            "dt": null,
            "fft_freq": null,
            "fft_ampl": null,
            "peak_freq": null,
            "peak_ampl": null,
            "compact": false
        },
        {
            "t": 28.679744005203247,
            "accel": [
                [
                    -6.35,
                    -4.602,
                    10.391
                ]
            ],
            "dist": [
                90.27361078515416
            ],
            "mass": [
                0.0,
                16.74,
                14.79
            ],
            "rpm": [
                4942,
                4785,
                4714,
                4757
            ],
            "audio": null,
            "dt": null,
            "fft_freq": null,
            "fft_ampl": null,
            "peak_freq": null,
            "peak_ampl": null,
            "compact": false
        },
        {
            "t": 29.16892099380493,
            "accel": [
                [
                    8.04,
                    -4.769,
                    10.688
                ]
            ],
            "dist": [
                90.29788282888822
            ],
            "mass": [
                0.0,
                16.52,
                14.95
            ],
            "rpm": [
                4757,
                4714,
                4614,
                4642
            ],
            "audio": null,
            "dt": null,
            "fft_freq": null,
            "fft_ampl": null,
            "peak_freq": null,
            "peak_ampl": null,
            "compact": false
        },
        {
            "t": 29.59636163711548,
            "accel": [
                [
                    0.11,
                    -2.614,
                    11.526
                ]
            ],
            "dist": [
                90.2977436391359
            ],
            "mass": [
                0.0,
                16.45,
                14.91
            ],
            "rpm": [
                4828,
                4700,
                4614,
                4771
            ],
            "audio": null,
            "dt": null,
            "fft_freq": null,
            "fft_ampl": null,
            "peak_freq": null,
            "peak_ampl": null,
            "compact": false
        }
    ]
}